mdssdk/__init__.py
mdssdk/analytics.py
mdssdk/constants.py
mdssdk/devicealias.py
mdssdk/fabric.py
mdssdk/fc.py
mdssdk/fcns.py
mdssdk/flogi.py
mdssdk/interface.py
mdssdk/module.py
mdssdk/portchannel.py
mdssdk/switch.py
mdssdk/transceiver.py
mdssdk/vsan.py
mdssdk/zone.py
mdssdk/zoneset.py
mdssdk/connection_manager/__init__.py
mdssdk/connection_manager/connect_netmiko.py
mdssdk/connection_manager/connect_nxapi.py
mdssdk/connection_manager/errors.py
mdssdk/nxapikeys/__init__.py
mdssdk/nxapikeys/devicealiaskeys.py
mdssdk/nxapikeys/fcaliaskeys.py
mdssdk/nxapikeys/featurekeys.py
mdssdk/nxapikeys/interfacekeys.py
mdssdk/nxapikeys/inventorykeys.py
mdssdk/nxapikeys/modulekeys.py
mdssdk/nxapikeys/portchanelkeys.py
mdssdk/nxapikeys/topologykeys.py
mdssdk/nxapikeys/versionkeys.py
mdssdk/nxapikeys/vsankeys.py
mdssdk/nxapikeys/zonekeys.py
mdssdk/parsers/__init__.py
mdssdk/parsers/device_alias/__init__.py
mdssdk/parsers/device_alias/show_da_database.py
mdssdk/parsers/device_alias/show_da_status.py
mdssdk/parsers/fcs/__init__.py
mdssdk/parsers/fcs/show_fcs_ie.py
mdssdk/parsers/interface/__init__.py
mdssdk/parsers/interface/show_interface_brief.py
mdssdk/parsers/interface/show_interface_counters_brief.py
mdssdk/parsers/interface/show_interface_counters_detailed.py
mdssdk/parsers/interface/show_interface_description.py
mdssdk/parsers/interface/show_interface_transceiver_detail.py
mdssdk/parsers/portchannel/__init__.py
mdssdk/parsers/portchannel/show_port_channel_database.py
mdssdk/parsers/portchannel/show_port_channel_database_detail.py
mdssdk/parsers/switch/__init__.py
mdssdk/parsers/switch/sh_process_acltcam_fe_input.py
mdssdk/parsers/switch/show_topology.py
mdssdk/parsers/vsan/__init__.py
mdssdk/parsers/vsan/show_vsan.py
mdssdk/parsers/vsan/show_vsan_membership.py
mdssdk/parsers/zone/__init__.py
mdssdk/parsers/zone/show_zone.py
mdssdk/parsers/zone/show_zone_status.py
mdssdk/parsers/zoneset/__init__.py
mdssdk/parsers/zoneset/show_zoneset.py
mdssdk-1.3.3.dist-info/AUTHORS.rst
mdssdk-1.3.3.dist-info/LICENSE
mdssdk-1.3.3.dist-info/METADATA
mdssdk-1.3.3.dist-info/WHEEL
mdssdk-1.3.3.dist-info/top_level.txt
mdssdk-1.3.3.dist-info/RECORD
