Metadata-Version: 2.1
Name: mdssdk
Version: 1.3.3
Summary: Python SDK for Cisco MDS Switches
Home-page: https://github.com/Cisco-SAN/mdslib
Author: Cisco Systems, Inc.
Author-email: subharad@cisco.com
License: http://www.apache.org/licenses/LICENSE-2.0
Platform: UNKNOWN
Classifier: Development Status :: 4 - Beta
Classifier: Intended Audience :: Developers
Classifier: License :: OSI Approved :: Apache Software License
Classifier: Natural Language :: English
Classifier: Programming Language :: Python :: 3.6
Classifier: Programming Language :: Python :: 3.7
Requires-Dist: requests
Requires-Dist: paramiko
Requires-Dist: m2r
Requires-Dist: sphinx (==2.4.2)
Requires-Dist: netmiko (>=3.1.0)
Requires-Dist: PTable
Requires-Dist: pyinputplus
Requires-Dist: xlsxwriter
